AUTHORS
CHANGES
COPYING
MANIFEST.in
README
VERSION
setup.py
pytides/__init__.py
pytides/astro.py
pytides/constituent.py
pytides/nodal_corrections.py
pytides/tide.py
pytides.egg-info/PKG-INFO
pytides.egg-info/SOURCES.txt
pytides.egg-info/dependency_links.txt
pytides.egg-info/requires.txt
pytides.egg-info/top_level.txt