Metadata-Version: 1.0
Name: pytides
Version: 0.0.4
Summary: Tidal analysis and prediction library.
Home-page: http://github.com/sam-cox/pytides
Author: Sam Cox
Author-email: sam.cox@cantab.net
License: MIT
Platform: UNKNOWN
